translation_finder/__init__.py
translation_finder/api.py
translation_finder/data.py
translation_finder/finder.py
translation_finder/py.typed
translation_finder/test_api.py
translation_finder/test_discovery.py
translation_finder/test_finder.py
translation_finder/test_results.py
translation_finder/discovery/__init__.py
translation_finder/discovery/base.py
translation_finder/discovery/files.py
translation_finder/discovery/result.py
translation_finder/discovery/transifex.py
translation_finder/test_data/calibre.txt
translation_finder/test_data/catalysm.txt
translation_finder/test_data/.tx/config
translation_finder/test_data/app/src/res/main/values/strings.xml
translation_finder/test_data/app/src/res/main/values-it/strings.xml
translation_finder/test_data/catkeys/cs.catkeys
translation_finder/test_data/catkeys/en.catkeys
translation_finder/test_data/dtd/cs.dtd
translation_finder/test_data/dtd/en.dtd
translation_finder/test_data/invalid/.tx/config
translation_finder/test_data/java/iso.properties
translation_finder/test_data/java/iso_cs.properties
translation_finder/test_data/java/utf-16.properties
translation_finder/test_data/java/utf-16_cs.properties
translation_finder/test_data/java/utf-8.properties
translation_finder/test_data/java/utf-8_cs.properties
translation_finder/test_data/json/bi-cs.json
translation_finder/test_data/json/bom-en.json
translation_finder/test_data/json/flat-en.json
translation_finder/test_data/json/go-cs.json
translation_finder/test_data/json/go-en.json
translation_finder/test_data/json/go-i18n-v2-en.json
translation_finder/test_data/json/gotext-en.json
translation_finder/test_data/json/i18next-en.json
translation_finder/test_data/json/i18nextv4-en.json
translation_finder/test_data/json/nested-en.json
translation_finder/test_data/json/nextcloud-en.json
translation_finder/test_data/json/resjson-en.json
translation_finder/test_data/json/webext-en.json
translation_finder/test_data/lang/cs.lang
translation_finder/test_data/lang/en.lang
translation_finder-2.24.dist-info/licenses/LICENSE
translation_finder-2.24.dist-info/METADATA
translation_finder-2.24.dist-info/WHEEL
translation_finder-2.24.dist-info/entry_points.txt
translation_finder-2.24.dist-info/top_level.txt
translation_finder-2.24.dist-info/RECORD
