Metadata-Version: 2.4
Name: translation-finder
Version: 2.24
Summary: A translation file finder used in Weblate.
Home-page: https://weblate.org/
Download-URL: https://github.com/WeblateOrg/translation-finder
Author: Michal Čihař
Author-email: Michal Čihař <michal@weblate.org>
License-Expression: GPL-3.0-or-later
Project-URL: Documentation, https://docs.weblate.org/
Project-URL: Download, https://github.com/WeblateOrg/translation-finder
Project-URL: Funding, https://weblate.org/donate/
Project-URL: Homepage, https://weblate.org/
Project-URL: Issue Tracker, https://github.com/WeblateOrg/translation-finder/issues
Project-URL: Source Code, https://github.com/WeblateOrg/translation-finder
Project-URL: Twitter, https://twitter.com/WeblateOrg
Keywords: i18n,l10n,gettext,weblate,translate
Platform: any
Classifier: Development Status :: 5 - Production/Stable
Classifier: Intended Audience :: Developers
Classifier: Operating System :: OS Independent
Classifier: Programming Language :: Python
Classifier: Programming Language :: Python :: 3
Classifier: Programming Language :: Python :: 3 :: Only
Classifier: Programming Language :: Python :: 3.11
Classifier: Programming Language :: Python :: 3.12
Classifier: Programming Language :: Python :: 3.13
Classifier: Programming Language :: Python :: 3.14
Classifier: Topic :: Software Development :: Internationalization
Classifier: Topic :: Software Development :: Localization
Classifier: Topic :: Utilities
Requires-Python: >=3.11
License-File: LICENSE
Requires-Dist: charset-normalizer<4.0,>2.0
Requires-Dist: ruamel.yaml
Requires-Dist: weblate-language-data>=2026.1
Provides-Extra: dev
Requires-Dist: translation-finder[lint,test,types]; extra == "dev"
Provides-Extra: lint
Requires-Dist: pre-commit==4.5.1; extra == "lint"
Provides-Extra: test
Requires-Dist: pytest==9.0.2; extra == "test"
Requires-Dist: pytest-cov==7.0.0; extra == "test"
Requires-Dist: pytest-github-actions-annotate-failures==0.3.0; extra == "test"
Provides-Extra: types
Requires-Dist: mypy==1.19.1; extra == "types"
Dynamic: download-url
Dynamic: license-file
